hypergol/__init__.py
hypergol/base_batch_processor.py
hypergol/base_data.py
hypergol/base_tensorflow_model.py
hypergol/base_tensorflow_model_block.py
hypergol/base_torch_model.py
hypergol/base_torch_model_block.py
hypergol/datachunk.py
hypergol/dataset.py
hypergol/dataset_chk_file.py
hypergol/dataset_def_file.py
hypergol/dataset_factory.py
hypergol/delayed.py
hypergol/hypergol_project.py
hypergol/job.py
hypergol/job_report.py
hypergol/logger.py
hypergol/name_string.py
hypergol/pipeline.py
hypergol/repo_data.py
hypergol/repr.py
hypergol/task.py
hypergol/tensorflow_model_manager.py
hypergol/torch_model_manager.py
hypergol/utils.py
hypergol/cli/__init__.py
hypergol/cli/create_data_model.py
hypergol/cli/create_model.py
hypergol/cli/create_model_block.py
hypergol/cli/create_old_data_model.py
hypergol/cli/create_pipeline.py
hypergol/cli/create_project.py
hypergol/cli/create_task.py
hypergol/cli/data_model_renderer.py
hypergol/cli/diff_data_model.py
hypergol/cli/list_datasets.py
hypergol/cli/templates/.gitignore.j2
hypergol/cli/templates/HypergolExample.ipynb
hypergol/cli/templates/LICENSE.j2
hypergol/cli/templates/README.md.j2
hypergol/cli/templates/__init__.py.j2
hypergol/cli/templates/batch_processor.py.j2
hypergol/cli/templates/batch_processor_torch.py.j2
hypergol/cli/templates/make_venv.sh.j2
hypergol/cli/templates/model.py.j2
hypergol/cli/templates/model_block.py.j2
hypergol/cli/templates/model_block_torch.py.j2
hypergol/cli/templates/model_torch.py.j2
hypergol/cli/templates/pipeline.py.j2
hypergol/cli/templates/pipeline.sh.j2
hypergol/cli/templates/pylintrc.j2
hypergol/cli/templates/requirements.txt.j2
hypergol/cli/templates/run_pylint.sh.j2
hypergol/cli/templates/run_tests.sh.j2
hypergol/cli/templates/serve_model.py.j2
hypergol/cli/templates/serve_model.sh.j2
hypergol/cli/templates/serve_model_torch.py.j2
hypergol/cli/templates/source.py.j2
hypergol/cli/templates/task.py.j2
hypergol/cli/templates/test_data_models.py.j2
hypergol/cli/templates/train_model.py.j2
hypergol-0.2.1.dist-info/METADATA
hypergol-0.2.1.dist-info/WHEEL
hypergol-0.2.1.dist-info/top_level.txt
hypergol-0.2.1.dist-info/RECORD
