Metadata-Version: 2.1
Name: hypergol
Version: 0.2.1
Summary: An opinionated multithreaded Data Science framework
Home-page: https://github.com/hypergol/hypergol
Author: Laszlo Sragner
Author-email: hypergol.developer@gmail.com
License: UNKNOWN
Platform: UNKNOWN
Classifier: Programming Language :: Python :: 3
Classifier: License :: OSI Approved :: MIT License
Classifier: Operating System :: OS Independent
Requires-Python: >=3.8
Requires-Dist: fire
Requires-Dist: Jinja2
Requires-Dist: GitPython
Requires-Dist: numpy (==1.19.2)
Requires-Dist: tensorflow (==2.5.0)
Requires-Dist: torch (==1.10.2)
Requires-Dist: tqdm
Requires-Dist: pydantic
Requires-Dist: fastapi
Requires-Dist: uvicorn
